viaggiatreno_ha/__init__.py
viaggiatreno_ha/trainline.py
viaggiatreno_ha-0.2.3.dist-info/licenses/LICENSE
viaggiatreno_ha-0.2.3.dist-info/METADATA
viaggiatreno_ha-0.2.3.dist-info/WHEEL
viaggiatreno_ha-0.2.3.dist-info/top_level.txt
viaggiatreno_ha-0.2.3.dist-info/RECORD
