Metadata-Version: 2.4
Name: viaggiatreno_ha
Version: 0.2.3
Summary: Viaggiatreno API wrapper to use with Home Assistant.
Author-email: Mattia Monga <mattia.monga@unimi.it>
License-Expression: GPL-3.0-or-later
Project-URL: GitHub, https://github.com/monga/viaggiatreno_ha
Project-URL: Issues, https://github.com/monga/viaggiatreno_ha/issues
Classifier: Programming Language :: Python :: 3
Classifier: Operating System :: OS Independent
Requires-Python: >=3.9
License-File: LICENSE
Requires-Dist: aiohttp
Dynamic: license-file
